sadire/__init__.py
sadire/sampling.py
sadire/test.py
sadire-0.1.5.dist-info/LICENSE
sadire-0.1.5.dist-info/METADATA
sadire-0.1.5.dist-info/WHEEL
sadire-0.1.5.dist-info/top_level.txt
sadire-0.1.5.dist-info/RECORD
