Metadata-Version: 2.1
Name: sadire
Version: 0.1.5
Summary: Sampling from scatter-plot visualizations
Home-page: https://github.com/wilsonjr/sadire
Author: Wilson Estecio Marcilio Junior
Author-email: wilson_jr@outlook.com
License: MIT
Platform: UNKNOWN
Requires-Dist: pyqtree
Requires-Dist: numpy
